{
  "_metadata": {
    "season": "2013-14",
    "year": 2014,
    "sources": {
      "standings": "NHL API (api-web.nhle.com)",
      "advanced": "Natural Stat Trick (naturalstattrick.com)",
      "specialTeams": "NHL Stats REST API (api.nhle.com/stats/rest)"
    },
    "fetchedAt": "2026-02-02T05:24:20.341121Z",
    "cupWinner": "LA",
    "cupFinalist": "NYR",
    "playoffTeams": 16
  },
  "teams": {
    "BOS": {
      "team": "BOS",
      "name": "Boston Bruins",
      "gp": 82,
      "w": 54,
      "l": 19,
      "otl": 9,
      "pts": 117,
      "ptsPct": 0.713,
      "gf": 261,
      "ga": 177,
      "gd": 84,
      "ppPct": 21.7,
      "pkPct": 83.7,
      "conf": "East",
      "div": "Atlantic",
      "homeW": 31,
      "homeL": 7,
      "homeOTL": 3,
      "roadW": 23,
      "roadL": 12,
      "roadOTL": 6,
      "cfPct": 53.85,
      "hdcfPct": 52.84,
      "scfPct": 53.9,
      "pdo": 1.025,
      "shPct": 8.46,
      "svPct": 93.99,
      "cf": 3875,
      "ca": 3321,
      "hdcf": 633,
      "hdca": 565,
      "hasAdvanced": true,
      "wonCup": false,
      "cupFinalist": false,
      "madePlayoffs": true,
      "playoffRoundsWon": 1
    },
    "ANA": {
      "team": "ANA",
      "name": "Anaheim Ducks",
      "gp": 82,
      "w": 54,
      "l": 20,
      "otl": 8,
      "pts": 116,
      "ptsPct": 0.707,
      "gf": 266,
      "ga": 209,
      "gd": 57,
      "ppPct": 16.0,
      "pkPct": 82.2,
      "conf": "West",
      "div": "Pacific",
      "homeW": 29,
      "homeL": 8,
      "homeOTL": 4,
      "roadW": 25,
      "roadL": 12,
      "roadOTL": 4,
      "cfPct": 49.97,
      "hdcfPct": 52.79,
      "scfPct": 50.71,
      "pdo": 1.023,
      "shPct": 9.79,
      "svPct": 92.53,
      "cf": 3555,
      "ca": 3559,
      "hdcf": 766,
      "hdca": 685,
      "hasAdvanced": true,
      "wonCup": false,
      "cupFinalist": false,
      "madePlayoffs": true,
      "playoffRoundsWon": 1
    },
    "COL": {
      "team": "COL",
      "name": "Colorado Avalanche",
      "gp": 82,
      "w": 52,
      "l": 22,
      "otl": 8,
      "pts": 112,
      "ptsPct": 0.683,
      "gf": 250,
      "ga": 220,
      "gd": 30,
      "ppPct": 19.8,
      "pkPct": 80.7,
      "conf": "West",
      "div": "Central",
      "homeW": 26,
      "homeL": 11,
      "homeOTL": 4,
      "roadW": 26,
      "roadL": 11,
      "roadOTL": 4,
      "cfPct": 46.85,
      "hdcfPct": 45.41,
      "scfPct": 46.86,
      "pdo": 1.018,
      "shPct": 8.8,
      "svPct": 92.95,
      "cf": 3417,
      "ca": 3876,
      "hdcf": 648,
      "hdca": 779,
      "hasAdvanced": true,
      "wonCup": false,
      "cupFinalist": false,
      "madePlayoffs": true,
      "playoffRoundsWon": 0
    },
    "STL": {
      "team": "STL",
      "name": "St. Louis Blues",
      "gp": 82,
      "w": 52,
      "l": 23,
      "otl": 7,
      "pts": 111,
      "ptsPct": 0.677,
      "gf": 248,
      "ga": 191,
      "gd": 57,
      "ppPct": 19.8,
      "pkPct": 85.7,
      "conf": "West",
      "div": "Central",
      "homeW": 28,
      "homeL": 9,
      "homeOTL": 4,
      "roadW": 24,
      "roadL": 14,
      "roadOTL": 3,
      "cfPct": 53.13,
      "hdcfPct": 53.84,
      "scfPct": 52.94,
      "pdo": 1.007,
      "shPct": 8.46,
      "svPct": 92.19,
      "cf": 3546,
      "ca": 3128,
      "hdcf": 596,
      "hdca": 511,
      "hasAdvanced": true,
      "wonCup": false,
      "cupFinalist": false,
      "madePlayoffs": true,
      "playoffRoundsWon": 0
    },
    "SJ": {
      "team": "SJ",
      "name": "San Jose Sharks",
      "gp": 82,
      "w": 51,
      "l": 22,
      "otl": 9,
      "pts": 111,
      "ptsPct": 0.677,
      "gf": 249,
      "ga": 200,
      "gd": 49,
      "ppPct": 17.2,
      "pkPct": 84.9,
      "conf": "West",
      "div": "Pacific",
      "homeW": 29,
      "homeL": 7,
      "homeOTL": 5,
      "roadW": 22,
      "roadL": 15,
      "roadOTL": 4,
      "cfPct": 53.53,
      "hdcfPct": 56.81,
      "scfPct": 57.5,
      "pdo": 0.997,
      "shPct": 7.5,
      "svPct": 92.2,
      "cf": 4098,
      "ca": 3557,
      "hdcf": 751,
      "hdca": 571,
      "hasAdvanced": true,
      "wonCup": false,
      "cupFinalist": false,
      "madePlayoffs": true,
      "playoffRoundsWon": 0
    },
    "PIT": {
      "team": "PIT",
      "name": "Pittsburgh Penguins",
      "gp": 82,
      "w": 51,
      "l": 24,
      "otl": 7,
      "pts": 109,
      "ptsPct": 0.665,
      "gf": 249,
      "ga": 207,
      "gd": 42,
      "ppPct": 23.4,
      "pkPct": 85.0,
      "conf": "East",
      "div": "Metropolitan",
      "homeW": 28,
      "homeL": 9,
      "homeOTL": 4,
      "roadW": 23,
      "roadL": 15,
      "roadOTL": 3,
      "cfPct": 48.64,
      "hdcfPct": 49.3,
      "scfPct": 50.24,
      "pdo": 1.001,
      "shPct": 8.3,
      "svPct": 91.76,
      "cf": 3335,
      "ca": 3521,
      "hdcf": 567,
      "hdca": 583,
      "hasAdvanced": true,
      "wonCup": false,
      "cupFinalist": false,
      "madePlayoffs": true,
      "playoffRoundsWon": 1
    },
    "CHI": {
      "team": "CHI",
      "name": "Chicago Blackhawks",
      "gp": 82,
      "w": 46,
      "l": 21,
      "otl": 15,
      "pts": 107,
      "ptsPct": 0.652,
      "gf": 267,
      "ga": 220,
      "gd": 47,
      "ppPct": 19.5,
      "pkPct": 81.5,
      "conf": "West",
      "div": "Central",
      "homeW": 27,
      "homeL": 7,
      "homeOTL": 7,
      "roadW": 19,
      "roadL": 14,
      "roadOTL": 8,
      "cfPct": 55.48,
      "hdcfPct": 55.95,
      "scfPct": 55.86,
      "pdo": 0.999,
      "shPct": 8.4,
      "svPct": 91.47,
      "cf": 3908,
      "ca": 3136,
      "hdcf": 743,
      "hdca": 585,
      "hasAdvanced": true,
      "wonCup": false,
      "cupFinalist": false,
      "madePlayoffs": true,
      "playoffRoundsWon": 2
    },
    "TB": {
      "team": "TB",
      "name": "Tampa Bay Lightning",
      "gp": 82,
      "w": 46,
      "l": 27,
      "otl": 9,
      "pts": 101,
      "ptsPct": 0.616,
      "gf": 240,
      "ga": 215,
      "gd": 25,
      "ppPct": 18.5,
      "pkPct": 80.7,
      "conf": "East",
      "div": "Atlantic",
      "homeW": 25,
      "homeL": 10,
      "homeOTL": 6,
      "roadW": 21,
      "roadL": 17,
      "roadOTL": 3,
      "cfPct": 50.96,
      "hdcfPct": 51.33,
      "scfPct": 51.24,
      "pdo": 1.006,
      "shPct": 7.82,
      "svPct": 92.76,
      "cf": 3553,
      "ca": 3419,
      "hdcf": 635,
      "hdca": 602,
      "hasAdvanced": true,
      "wonCup": false,
      "cupFinalist": false,
      "madePlayoffs": true,
      "playoffRoundsWon": 0
    },
    "MTL": {
      "team": "MTL",
      "name": "Montr\u00e9al Canadiens",
      "gp": 82,
      "w": 46,
      "l": 28,
      "otl": 8,
      "pts": 100,
      "ptsPct": 0.61,
      "gf": 215,
      "ga": 204,
      "gd": 11,
      "ppPct": 17.2,
      "pkPct": 85.1,
      "conf": "East",
      "div": "Atlantic",
      "homeW": 23,
      "homeL": 13,
      "homeOTL": 5,
      "roadW": 23,
      "roadL": 15,
      "roadOTL": 3,
      "cfPct": 46.74,
      "hdcfPct": 49.18,
      "scfPct": 46.69,
      "pdo": 1.005,
      "shPct": 7.54,
      "svPct": 93.0,
      "cf": 3373,
      "ca": 3844,
      "hdcf": 661,
      "hdca": 683,
      "hasAdvanced": true,
      "wonCup": false,
      "cupFinalist": false,
      "madePlayoffs": true,
      "playoffRoundsWon": 2
    },
    "LA": {
      "team": "LA",
      "name": "Los Angeles Kings",
      "gp": 82,
      "w": 46,
      "l": 28,
      "otl": 8,
      "pts": 100,
      "ptsPct": 0.61,
      "gf": 206,
      "ga": 174,
      "gd": 32,
      "ppPct": 15.1,
      "pkPct": 83.1,
      "conf": "West",
      "div": "Pacific",
      "homeW": 23,
      "homeL": 14,
      "homeOTL": 4,
      "roadW": 23,
      "roadL": 14,
      "roadOTL": 4,
      "cfPct": 56.82,
      "hdcfPct": 54.02,
      "scfPct": 54.93,
      "pdo": 1.001,
      "shPct": 6.6,
      "svPct": 93.51,
      "cf": 3890,
      "ca": 2956,
      "hdcf": 658,
      "hdca": 560,
      "hasAdvanced": true,
      "wonCup": true,
      "cupFinalist": false,
      "madePlayoffs": true,
      "playoffRoundsWon": 4
    },
    "MIN": {
      "team": "MIN",
      "name": "Minnesota Wild",
      "gp": 82,
      "w": 43,
      "l": 27,
      "otl": 12,
      "pts": 98,
      "ptsPct": 0.598,
      "gf": 207,
      "ga": 206,
      "gd": 1,
      "ppPct": 17.9,
      "pkPct": 78.8,
      "conf": "West",
      "div": "Central",
      "homeW": 26,
      "homeL": 10,
      "homeOTL": 5,
      "roadW": 17,
      "roadL": 17,
      "roadOTL": 7,
      "cfPct": 48.8,
      "hdcfPct": 51.97,
      "scfPct": 50.66,
      "pdo": 1.011,
      "shPct": 7.91,
      "svPct": 93.21,
      "cf": 3183,
      "ca": 3340,
      "hdcf": 541,
      "hdca": 500,
      "hasAdvanced": true,
      "wonCup": false,
      "cupFinalist": false,
      "madePlayoffs": true,
      "playoffRoundsWon": 1
    },
    "NYR": {
      "team": "NYR",
      "name": "New York Rangers",
      "gp": 82,
      "w": 45,
      "l": 31,
      "otl": 6,
      "pts": 96,
      "ptsPct": 0.585,
      "gf": 218,
      "ga": 193,
      "gd": 25,
      "ppPct": 18.2,
      "pkPct": 85.3,
      "conf": "East",
      "div": "Metropolitan",
      "homeW": 20,
      "homeL": 17,
      "homeOTL": 4,
      "roadW": 25,
      "roadL": 14,
      "roadOTL": 2,
      "cfPct": 52.4,
      "hdcfPct": 54.19,
      "scfPct": 52.59,
      "pdo": 0.997,
      "shPct": 6.68,
      "svPct": 93.07,
      "cf": 3854,
      "ca": 3501,
      "hdcf": 835,
      "hdca": 706,
      "hasAdvanced": true,
      "wonCup": false,
      "cupFinalist": true,
      "madePlayoffs": true,
      "playoffRoundsWon": 3
    },
    "PHI": {
      "team": "PHI",
      "name": "Philadelphia Flyers",
      "gp": 82,
      "w": 42,
      "l": 30,
      "otl": 10,
      "pts": 94,
      "ptsPct": 0.573,
      "gf": 236,
      "ga": 235,
      "gd": 1,
      "ppPct": 19.7,
      "pkPct": 84.8,
      "conf": "East",
      "div": "Metropolitan",
      "homeW": 24,
      "homeL": 14,
      "homeOTL": 3,
      "roadW": 18,
      "roadL": 16,
      "roadOTL": 7,
      "cfPct": 49.97,
      "hdcfPct": 49.69,
      "scfPct": 48.36,
      "pdo": 1.003,
      "shPct": 8.02,
      "svPct": 92.25,
      "cf": 3512,
      "ca": 3516,
      "hdcf": 561,
      "hdca": 568,
      "hasAdvanced": true,
      "wonCup": false,
      "cupFinalist": false,
      "madePlayoffs": true,
      "playoffRoundsWon": 0
    },
    "CBJ": {
      "team": "CBJ",
      "name": "Columbus Blue Jackets",
      "gp": 82,
      "w": 43,
      "l": 32,
      "otl": 7,
      "pts": 93,
      "ptsPct": 0.567,
      "gf": 231,
      "ga": 216,
      "gd": 15,
      "ppPct": 19.3,
      "pkPct": 82.1,
      "conf": "East",
      "div": "Metropolitan",
      "homeW": 22,
      "homeL": 15,
      "homeOTL": 4,
      "roadW": 21,
      "roadL": 17,
      "roadOTL": 3,
      "cfPct": 49.91,
      "hdcfPct": 51.6,
      "scfPct": 51.88,
      "pdo": 1.008,
      "shPct": 8.01,
      "svPct": 92.78,
      "cf": 3348,
      "ca": 3360,
      "hdcf": 597,
      "hdca": 560,
      "hasAdvanced": true,
      "wonCup": false,
      "cupFinalist": false,
      "madePlayoffs": true,
      "playoffRoundsWon": 0
    },
    "DET": {
      "team": "DET",
      "name": "Detroit Red Wings",
      "gp": 82,
      "w": 39,
      "l": 28,
      "otl": 15,
      "pts": 93,
      "ptsPct": 0.567,
      "gf": 222,
      "ga": 230,
      "gd": -8,
      "ppPct": 17.7,
      "pkPct": 83.1,
      "conf": "East",
      "div": "Atlantic",
      "homeW": 18,
      "homeL": 13,
      "homeOTL": 10,
      "roadW": 21,
      "roadL": 15,
      "roadOTL": 5,
      "cfPct": 51.41,
      "hdcfPct": 48.2,
      "scfPct": 51.62,
      "pdo": 1.002,
      "shPct": 8.17,
      "svPct": 92.03,
      "cf": 3320,
      "ca": 3138,
      "hdcf": 550,
      "hdca": 591,
      "hasAdvanced": true,
      "wonCup": false,
      "cupFinalist": false,
      "madePlayoffs": true,
      "playoffRoundsWon": 0
    },
    "DAL": {
      "team": "DAL",
      "name": "Dallas Stars",
      "gp": 82,
      "w": 40,
      "l": 31,
      "otl": 11,
      "pts": 91,
      "ptsPct": 0.555,
      "gf": 235,
      "ga": 228,
      "gd": 7,
      "ppPct": 15.9,
      "pkPct": 81.4,
      "conf": "West",
      "div": "Central",
      "homeW": 23,
      "homeL": 11,
      "homeOTL": 7,
      "roadW": 17,
      "roadL": 20,
      "roadOTL": 4,
      "cfPct": 50.5,
      "hdcfPct": 49.44,
      "scfPct": 51.1,
      "pdo": 1.003,
      "shPct": 8.17,
      "svPct": 92.09,
      "cf": 3704,
      "ca": 3631,
      "hdcf": 704,
      "hdca": 720,
      "hasAdvanced": true,
      "wonCup": false,
      "cupFinalist": false,
      "madePlayoffs": true,
      "playoffRoundsWon": 0
    },
    "WSH": {
      "team": "WSH",
      "name": "Washington Capitals",
      "gp": 82,
      "w": 38,
      "l": 30,
      "otl": 14,
      "pts": 90,
      "ptsPct": 0.549,
      "gf": 235,
      "ga": 240,
      "gd": -5,
      "ppPct": 23.4,
      "pkPct": 82.0,
      "conf": "East",
      "div": "Metropolitan",
      "homeW": 21,
      "homeL": 13,
      "homeOTL": 7,
      "roadW": 17,
      "roadL": 17,
      "roadOTL": 7,
      "cfPct": 47.67,
      "hdcfPct": 47.94,
      "scfPct": 47.42,
      "pdo": 1.002,
      "shPct": 7.69,
      "svPct": 92.47,
      "cf": 3366,
      "ca": 3695,
      "hdcf": 583,
      "hdca": 633,
      "hasAdvanced": true,
      "wonCup": false,
      "cupFinalist": false,
      "madePlayoffs": false,
      "playoffRoundsWon": 0
    },
    "ARI": {
      "team": "ARI",
      "name": "Phoenix Coyotes",
      "gp": 82,
      "w": 37,
      "l": 30,
      "otl": 15,
      "pts": 89,
      "ptsPct": 0.543,
      "gf": 216,
      "ga": 231,
      "gd": -15,
      "ppPct": 19.9,
      "pkPct": 79.0,
      "conf": "West",
      "div": "Pacific",
      "homeW": 22,
      "homeL": 14,
      "homeOTL": 5,
      "roadW": 15,
      "roadL": 16,
      "roadOTL": 10,
      "cfPct": 50.52,
      "hdcfPct": 45.79,
      "scfPct": 47.78,
      "pdo": 1.002,
      "shPct": 7.24,
      "svPct": 92.96,
      "cf": 3609,
      "ca": 3535,
      "hdcf": 604,
      "hdca": 715,
      "hasAdvanced": true,
      "wonCup": false,
      "cupFinalist": false,
      "madePlayoffs": false,
      "playoffRoundsWon": 0
    },
    "NSH": {
      "team": "NSH",
      "name": "Nashville Predators",
      "gp": 82,
      "w": 38,
      "l": 32,
      "otl": 12,
      "pts": 88,
      "ptsPct": 0.537,
      "gf": 216,
      "ga": 242,
      "gd": -26,
      "ppPct": 19.2,
      "pkPct": 80.3,
      "conf": "West",
      "div": "Central",
      "homeW": 19,
      "homeL": 17,
      "homeOTL": 5,
      "roadW": 19,
      "roadL": 15,
      "roadOTL": 7,
      "cfPct": 48.44,
      "hdcfPct": 53.15,
      "scfPct": 50.28,
      "pdo": 0.99,
      "shPct": 7.95,
      "svPct": 91.01,
      "cf": 3420,
      "ca": 3640,
      "hdcf": 607,
      "hdca": 535,
      "hasAdvanced": true,
      "wonCup": false,
      "cupFinalist": false,
      "madePlayoffs": false,
      "playoffRoundsWon": 0
    },
    "NJ": {
      "team": "NJ",
      "name": "New Jersey Devils",
      "gp": 82,
      "w": 35,
      "l": 29,
      "otl": 18,
      "pts": 88,
      "ptsPct": 0.537,
      "gf": 197,
      "ga": 208,
      "gd": -11,
      "ppPct": 19.5,
      "pkPct": 86.4,
      "conf": "East",
      "div": "Metropolitan",
      "homeW": 21,
      "homeL": 11,
      "homeOTL": 9,
      "roadW": 14,
      "roadL": 18,
      "roadOTL": 9,
      "cfPct": 54.4,
      "hdcfPct": 58.27,
      "scfPct": 55.61,
      "pdo": 0.986,
      "shPct": 7.15,
      "svPct": 91.44,
      "cf": 3237,
      "ca": 2713,
      "hdcf": 634,
      "hdca": 454,
      "hasAdvanced": true,
      "wonCup": false,
      "cupFinalist": false,
      "madePlayoffs": false,
      "playoffRoundsWon": 0
    },
    "OTT": {
      "team": "OTT",
      "name": "Ottawa Senators",
      "gp": 82,
      "w": 37,
      "l": 31,
      "otl": 14,
      "pts": 88,
      "ptsPct": 0.537,
      "gf": 236,
      "ga": 265,
      "gd": -29,
      "ppPct": 18.5,
      "pkPct": 80.9,
      "conf": "East",
      "div": "Atlantic",
      "homeW": 18,
      "homeL": 17,
      "homeOTL": 6,
      "roadW": 19,
      "roadL": 14,
      "roadOTL": 8,
      "cfPct": 52.42,
      "hdcfPct": 46.43,
      "scfPct": 49.63,
      "pdo": 0.995,
      "shPct": 7.47,
      "svPct": 92.06,
      "cf": 3938,
      "ca": 3575,
      "hdcf": 604,
      "hdca": 697,
      "hasAdvanced": true,
      "wonCup": false,
      "cupFinalist": false,
      "madePlayoffs": false,
      "playoffRoundsWon": 0
    },
    "WPG": {
      "team": "WPG",
      "name": "Winnipeg Jets",
      "gp": 82,
      "w": 37,
      "l": 35,
      "otl": 10,
      "pts": 84,
      "ptsPct": 0.512,
      "gf": 227,
      "ga": 237,
      "gd": -10,
      "ppPct": 15.4,
      "pkPct": 83.2,
      "conf": "West",
      "div": "Central",
      "homeW": 18,
      "homeL": 17,
      "homeOTL": 6,
      "roadW": 19,
      "roadL": 18,
      "roadOTL": 4,
      "cfPct": 50.04,
      "hdcfPct": 51.33,
      "scfPct": 50.55,
      "pdo": 0.994,
      "shPct": 7.86,
      "svPct": 91.53,
      "cf": 3646,
      "ca": 3640,
      "hdcf": 714,
      "hdca": 677,
      "hasAdvanced": true,
      "wonCup": false,
      "cupFinalist": false,
      "madePlayoffs": false,
      "playoffRoundsWon": 0
    },
    "TOR": {
      "team": "TOR",
      "name": "Toronto Maple Leafs",
      "gp": 82,
      "w": 38,
      "l": 36,
      "otl": 8,
      "pts": 84,
      "ptsPct": 0.512,
      "gf": 231,
      "ga": 256,
      "gd": -25,
      "ppPct": 19.8,
      "pkPct": 78.4,
      "conf": "East",
      "div": "Atlantic",
      "homeW": 24,
      "homeL": 16,
      "homeOTL": 1,
      "roadW": 14,
      "roadL": 20,
      "roadOTL": 7,
      "cfPct": 42.82,
      "hdcfPct": 41.79,
      "scfPct": 43.24,
      "pdo": 1.012,
      "shPct": 8.48,
      "svPct": 92.72,
      "cf": 3258,
      "ca": 4350,
      "hdcf": 524,
      "hdca": 730,
      "hasAdvanced": true,
      "wonCup": false,
      "cupFinalist": false,
      "madePlayoffs": false,
      "playoffRoundsWon": 0
    },
    "CAR": {
      "team": "CAR",
      "name": "Carolina Hurricanes",
      "gp": 82,
      "w": 36,
      "l": 35,
      "otl": 11,
      "pts": 83,
      "ptsPct": 0.506,
      "gf": 207,
      "ga": 230,
      "gd": -23,
      "ppPct": 14.6,
      "pkPct": 81.7,
      "conf": "East",
      "div": "Metropolitan",
      "homeW": 18,
      "homeL": 17,
      "homeOTL": 6,
      "roadW": 18,
      "roadL": 18,
      "roadOTL": 5,
      "cfPct": 50.3,
      "hdcfPct": 48.27,
      "scfPct": 48.88,
      "pdo": 0.994,
      "shPct": 6.82,
      "svPct": 92.6,
      "cf": 3820,
      "ca": 3774,
      "hdcf": 696,
      "hdca": 746,
      "hasAdvanced": true,
      "wonCup": false,
      "cupFinalist": false,
      "madePlayoffs": false,
      "playoffRoundsWon": 0
    },
    "VAN": {
      "team": "VAN",
      "name": "Vancouver Canucks",
      "gp": 82,
      "w": 36,
      "l": 35,
      "otl": 11,
      "pts": 83,
      "ptsPct": 0.506,
      "gf": 196,
      "ga": 223,
      "gd": -27,
      "ppPct": 15.2,
      "pkPct": 83.2,
      "conf": "West",
      "div": "Pacific",
      "homeW": 20,
      "homeL": 15,
      "homeOTL": 6,
      "roadW": 16,
      "roadL": 20,
      "roadOTL": 5,
      "cfPct": 51.36,
      "hdcfPct": 51.14,
      "scfPct": 49.41,
      "pdo": 0.995,
      "shPct": 7.26,
      "svPct": 92.24,
      "cf": 3699,
      "ca": 3503,
      "hdcf": 649,
      "hdca": 620,
      "hasAdvanced": true,
      "wonCup": false,
      "cupFinalist": false,
      "madePlayoffs": false,
      "playoffRoundsWon": 0
    },
    "NYI": {
      "team": "NYI",
      "name": "New York Islanders",
      "gp": 82,
      "w": 34,
      "l": 37,
      "otl": 11,
      "pts": 79,
      "ptsPct": 0.482,
      "gf": 225,
      "ga": 267,
      "gd": -42,
      "ppPct": 17.8,
      "pkPct": 78.1,
      "conf": "East",
      "div": "Metropolitan",
      "homeW": 13,
      "homeL": 19,
      "homeOTL": 9,
      "roadW": 21,
      "roadL": 18,
      "roadOTL": 2,
      "cfPct": 49.5,
      "hdcfPct": 48.95,
      "scfPct": 49.07,
      "pdo": 0.984,
      "shPct": 7.3,
      "svPct": 91.1,
      "cf": 3620,
      "ca": 3693,
      "hdcf": 772,
      "hdca": 805,
      "hasAdvanced": true,
      "wonCup": false,
      "cupFinalist": false,
      "madePlayoffs": false,
      "playoffRoundsWon": 0
    },
    "CGY": {
      "team": "CGY",
      "name": "Calgary Flames",
      "gp": 82,
      "w": 35,
      "l": 40,
      "otl": 7,
      "pts": 77,
      "ptsPct": 0.47,
      "gf": 209,
      "ga": 241,
      "gd": -32,
      "ppPct": 15.7,
      "pkPct": 81.7,
      "conf": "West",
      "div": "Pacific",
      "homeW": 19,
      "homeL": 19,
      "homeOTL": 3,
      "roadW": 16,
      "roadL": 21,
      "roadOTL": 4,
      "cfPct": 46.32,
      "hdcfPct": 45.04,
      "scfPct": 45.5,
      "pdo": 0.988,
      "shPct": 7.87,
      "svPct": 90.89,
      "cf": 3320,
      "ca": 3848,
      "hdcf": 559,
      "hdca": 682,
      "hasAdvanced": true,
      "wonCup": false,
      "cupFinalist": false,
      "madePlayoffs": false,
      "playoffRoundsWon": 0
    },
    "EDM": {
      "team": "EDM",
      "name": "Edmonton Oilers",
      "gp": 82,
      "w": 29,
      "l": 44,
      "otl": 9,
      "pts": 67,
      "ptsPct": 0.409,
      "gf": 203,
      "ga": 270,
      "gd": -67,
      "ppPct": 17.0,
      "pkPct": 82.1,
      "conf": "West",
      "div": "Pacific",
      "homeW": 16,
      "homeL": 22,
      "homeOTL": 3,
      "roadW": 13,
      "roadL": 22,
      "roadOTL": 6,
      "cfPct": 44.33,
      "hdcfPct": 46.36,
      "scfPct": 45.66,
      "pdo": 0.991,
      "shPct": 7.75,
      "svPct": 91.33,
      "cf": 3105,
      "ca": 3900,
      "hdcf": 611,
      "hdca": 707,
      "hasAdvanced": true,
      "wonCup": false,
      "cupFinalist": false,
      "madePlayoffs": false,
      "playoffRoundsWon": 0
    },
    "FLA": {
      "team": "FLA",
      "name": "Florida Panthers",
      "gp": 82,
      "w": 29,
      "l": 45,
      "otl": 8,
      "pts": 66,
      "ptsPct": 0.402,
      "gf": 196,
      "ga": 268,
      "gd": -72,
      "ppPct": 10.0,
      "pkPct": 76.0,
      "conf": "East",
      "div": "Atlantic",
      "homeW": 16,
      "homeL": 20,
      "homeOTL": 5,
      "roadW": 13,
      "roadL": 25,
      "roadOTL": 3,
      "cfPct": 50.91,
      "hdcfPct": 48.2,
      "scfPct": 49.94,
      "pdo": 0.982,
      "shPct": 7.33,
      "svPct": 90.87,
      "cf": 3528,
      "ca": 3402,
      "hdcf": 604,
      "hdca": 649,
      "hasAdvanced": true,
      "wonCup": false,
      "cupFinalist": false,
      "madePlayoffs": false,
      "playoffRoundsWon": 0
    },
    "BUF": {
      "team": "BUF",
      "name": "Buffalo Sabres",
      "gp": 82,
      "w": 21,
      "l": 51,
      "otl": 10,
      "pts": 52,
      "ptsPct": 0.317,
      "gf": 157,
      "ga": 248,
      "gd": -91,
      "ppPct": 14.1,
      "pkPct": 81.4,
      "conf": "East",
      "div": "Atlantic",
      "homeW": 13,
      "homeL": 21,
      "homeOTL": 7,
      "roadW": 8,
      "roadL": 30,
      "roadOTL": 3,
      "cfPct": 43.09,
      "hdcfPct": 42.92,
      "scfPct": 41.41,
      "pdo": 0.982,
      "shPct": 5.83,
      "svPct": 92.33,
      "cf": 3013,
      "ca": 3979,
      "hdcf": 570,
      "hdca": 758,
      "hasAdvanced": true,
      "wonCup": false,
      "cupFinalist": false,
      "madePlayoffs": false,
      "playoffRoundsWon": 0
    }
  }
}