{
  "_metadata": {
    "season": "2015-16",
    "year": 2016,
    "sources": {
      "standings": "NHL API (api-web.nhle.com)",
      "advanced": "Natural Stat Trick (naturalstattrick.com)"
    },
    "fetchedAt": "2026-02-01T22:56:14.917473Z",
    "cupWinner": "PIT",
    "cupFinalist": "SJ"
  },
  "teams": {
    "WSH": {
      "team": "WSH",
      "name": "Washington Capitals",
      "gp": 81,
      "w": 56,
      "l": 17,
      "otl": 8,
      "pts": 120,
      "ptsPct": 0.741,
      "gf": 252,
      "ga": 191,
      "gd": 61,
      "ppPct": 0,
      "pkPct": 0,
      "conf": "East",
      "div": "Metropolitan",
      "homeW": 29,
      "homeL": 7,
      "homeOTL": 4,
      "roadW": 27,
      "roadL": 10,
      "roadOTL": 4,
      "cfPct": 51.04,
      "hdcfPct": 50.94,
      "scfPct": 51.45,
      "pdo": 1.012,
      "shPct": 8.33,
      "svPct": 92.89,
      "cf": 3691,
      "ca": 3541,
      "hdcf": 677,
      "hdca": 652,
      "hasAdvanced": true,
      "wonCup": false,
      "cupFinalist": false
    },
    "DAL": {
      "team": "DAL",
      "name": "Dallas Stars",
      "gp": 82,
      "w": 50,
      "l": 23,
      "otl": 9,
      "pts": 109,
      "ptsPct": 0.665,
      "gf": 267,
      "ga": 230,
      "gd": 37,
      "ppPct": 0,
      "pkPct": 0,
      "conf": "West",
      "div": "Central",
      "homeW": 28,
      "homeL": 11,
      "homeOTL": 2,
      "roadW": 22,
      "roadL": 12,
      "roadOTL": 7,
      "cfPct": 52.56,
      "hdcfPct": 51.76,
      "scfPct": 53.23,
      "pdo": 0.997,
      "shPct": 8.03,
      "svPct": 91.67,
      "cf": 4034,
      "ca": 3641,
      "hdcf": 793,
      "hdca": 739,
      "hasAdvanced": true,
      "wonCup": false,
      "cupFinalist": false
    },
    "STL": {
      "team": "STL",
      "name": "St. Louis Blues",
      "gp": 82,
      "w": 49,
      "l": 24,
      "otl": 9,
      "pts": 107,
      "ptsPct": 0.652,
      "gf": 224,
      "ga": 201,
      "gd": 23,
      "ppPct": 0,
      "pkPct": 0,
      "conf": "West",
      "div": "Central",
      "homeW": 24,
      "homeL": 13,
      "homeOTL": 4,
      "roadW": 25,
      "roadL": 11,
      "roadOTL": 5,
      "cfPct": 52.0,
      "hdcfPct": 51.15,
      "scfPct": 52.1,
      "pdo": 1.002,
      "shPct": 7.02,
      "svPct": 93.14,
      "cf": 3621,
      "ca": 3342,
      "hdcf": 669,
      "hdca": 639,
      "hasAdvanced": true,
      "wonCup": false,
      "cupFinalist": false
    },
    "PIT": {
      "team": "PIT",
      "name": "Pittsburgh Penguins",
      "gp": 82,
      "w": 48,
      "l": 26,
      "otl": 8,
      "pts": 104,
      "ptsPct": 0.634,
      "gf": 245,
      "ga": 203,
      "gd": 42,
      "ppPct": 0,
      "pkPct": 0,
      "conf": "East",
      "div": "Metropolitan",
      "homeW": 26,
      "homeL": 11,
      "homeOTL": 4,
      "roadW": 22,
      "roadL": 15,
      "roadOTL": 4,
      "cfPct": 52.72,
      "hdcfPct": 55.13,
      "scfPct": 54.97,
      "pdo": 1.006,
      "shPct": 7.53,
      "svPct": 93.06,
      "cf": 3778,
      "ca": 3388,
      "hdcf": 742,
      "hdca": 604,
      "hasAdvanced": true,
      "wonCup": true,
      "cupFinalist": false
    },
    "CHI": {
      "team": "CHI",
      "name": "Chicago Blackhawks",
      "gp": 82,
      "w": 47,
      "l": 26,
      "otl": 9,
      "pts": 103,
      "ptsPct": 0.628,
      "gf": 235,
      "ga": 209,
      "gd": 26,
      "ppPct": 0,
      "pkPct": 0,
      "conf": "West",
      "div": "Central",
      "homeW": 26,
      "homeL": 11,
      "homeOTL": 4,
      "roadW": 21,
      "roadL": 15,
      "roadOTL": 5,
      "cfPct": 50.64,
      "hdcfPct": 47.16,
      "scfPct": 49.73,
      "pdo": 0.996,
      "shPct": 6.75,
      "svPct": 92.82,
      "cf": 3681,
      "ca": 3588,
      "hdcf": 632,
      "hdca": 708,
      "hasAdvanced": true,
      "wonCup": false,
      "cupFinalist": false
    },
    "FLA": {
      "team": "FLA",
      "name": "Florida Panthers",
      "gp": 82,
      "w": 47,
      "l": 26,
      "otl": 9,
      "pts": 103,
      "ptsPct": 0.628,
      "gf": 239,
      "ga": 203,
      "gd": 36,
      "ppPct": 0,
      "pkPct": 0,
      "conf": "East",
      "div": "Atlantic",
      "homeW": 25,
      "homeL": 11,
      "homeOTL": 5,
      "roadW": 22,
      "roadL": 15,
      "roadOTL": 4,
      "cfPct": 48.68,
      "hdcfPct": 49.36,
      "scfPct": 50.19,
      "pdo": 1.021,
      "shPct": 8.84,
      "svPct": 93.23,
      "cf": 3106,
      "ca": 3274,
      "hdcf": 583,
      "hdca": 598,
      "hasAdvanced": true,
      "wonCup": false,
      "cupFinalist": false
    },
    "LA": {
      "team": "LA",
      "name": "Los Angeles Kings",
      "gp": 82,
      "w": 48,
      "l": 28,
      "otl": 6,
      "pts": 102,
      "ptsPct": 0.622,
      "gf": 225,
      "ga": 195,
      "gd": 30,
      "ppPct": 0,
      "pkPct": 0,
      "conf": "West",
      "div": "Pacific",
      "homeW": 26,
      "homeL": 12,
      "homeOTL": 3,
      "roadW": 22,
      "roadL": 16,
      "roadOTL": 3,
      "cfPct": 56.37,
      "hdcfPct": 55.53,
      "scfPct": 55.1,
      "pdo": 0.997,
      "shPct": 6.78,
      "svPct": 92.93,
      "cf": 4084,
      "ca": 3161,
      "hdcf": 723,
      "hdca": 579,
      "hasAdvanced": true,
      "wonCup": false,
      "cupFinalist": false
    },
    "ANA": {
      "team": "ANA",
      "name": "Anaheim Ducks",
      "gp": 81,
      "w": 45,
      "l": 25,
      "otl": 11,
      "pts": 101,
      "ptsPct": 0.623,
      "gf": 216,
      "ga": 192,
      "gd": 24,
      "ppPct": 0,
      "pkPct": 0,
      "conf": "West",
      "div": "Pacific",
      "homeW": 25,
      "homeL": 10,
      "homeOTL": 6,
      "roadW": 20,
      "roadL": 15,
      "roadOTL": 5,
      "cfPct": 52.37,
      "hdcfPct": 51.74,
      "scfPct": 52.8,
      "pdo": 0.99,
      "shPct": 6.64,
      "svPct": 92.39,
      "cf": 3642,
      "ca": 3313,
      "hdcf": 668,
      "hdca": 623,
      "hasAdvanced": true,
      "wonCup": false,
      "cupFinalist": false
    },
    "NYR": {
      "team": "NYR",
      "name": "New York Rangers",
      "gp": 82,
      "w": 46,
      "l": 27,
      "otl": 9,
      "pts": 101,
      "ptsPct": 0.616,
      "gf": 236,
      "ga": 217,
      "gd": 19,
      "ppPct": 0,
      "pkPct": 0,
      "conf": "East",
      "div": "Metropolitan",
      "homeW": 27,
      "homeL": 10,
      "homeOTL": 4,
      "roadW": 19,
      "roadL": 17,
      "roadOTL": 5,
      "cfPct": 47.36,
      "hdcfPct": 46.91,
      "scfPct": 47.16,
      "pdo": 1.024,
      "shPct": 9.01,
      "svPct": 93.44,
      "cf": 3432,
      "ca": 3814,
      "hdcf": 714,
      "hdca": 808,
      "hasAdvanced": true,
      "wonCup": false,
      "cupFinalist": false
    },
    "NYI": {
      "team": "NYI",
      "name": "New York Islanders",
      "gp": 81,
      "w": 45,
      "l": 26,
      "otl": 10,
      "pts": 100,
      "ptsPct": 0.617,
      "gf": 230,
      "ga": 211,
      "gd": 19,
      "ppPct": 0,
      "pkPct": 0,
      "conf": "East",
      "div": "Metropolitan",
      "homeW": 25,
      "homeL": 10,
      "homeOTL": 5,
      "roadW": 20,
      "roadL": 16,
      "roadOTL": 5,
      "cfPct": 49.51,
      "hdcfPct": 48.57,
      "scfPct": 48.41,
      "pdo": 1.007,
      "shPct": 8.11,
      "svPct": 92.57,
      "cf": 3678,
      "ca": 3751,
      "hdcf": 715,
      "hdca": 757,
      "hasAdvanced": true,
      "wonCup": false,
      "cupFinalist": false
    },
    "SJ": {
      "team": "SJ",
      "name": "San Jose Sharks",
      "gp": 82,
      "w": 46,
      "l": 30,
      "otl": 6,
      "pts": 98,
      "ptsPct": 0.598,
      "gf": 241,
      "ga": 210,
      "gd": 31,
      "ppPct": 0,
      "pkPct": 0,
      "conf": "West",
      "div": "Pacific",
      "homeW": 18,
      "homeL": 20,
      "homeOTL": 3,
      "roadW": 28,
      "roadL": 10,
      "roadOTL": 3,
      "cfPct": 51.69,
      "hdcfPct": 57.88,
      "scfPct": 54.59,
      "pdo": 1.0,
      "shPct": 7.69,
      "svPct": 92.3,
      "cf": 3661,
      "ca": 3422,
      "hdcf": 790,
      "hdca": 575,
      "hasAdvanced": true,
      "wonCup": false,
      "cupFinalist": true
    },
    "TB": {
      "team": "TB",
      "name": "Tampa Bay Lightning",
      "gp": 82,
      "w": 46,
      "l": 31,
      "otl": 5,
      "pts": 97,
      "ptsPct": 0.591,
      "gf": 227,
      "ga": 201,
      "gd": 26,
      "ppPct": 0,
      "pkPct": 0,
      "conf": "East",
      "div": "Atlantic",
      "homeW": 25,
      "homeL": 13,
      "homeOTL": 3,
      "roadW": 21,
      "roadL": 18,
      "roadOTL": 2,
      "cfPct": 52.19,
      "hdcfPct": 52.53,
      "scfPct": 52.57,
      "pdo": 1.009,
      "shPct": 7.93,
      "svPct": 92.95,
      "cf": 3551,
      "ca": 3253,
      "hdcf": 624,
      "hdca": 564,
      "hasAdvanced": true,
      "wonCup": false,
      "cupFinalist": false
    },
    "NSH": {
      "team": "NSH",
      "name": "Nashville Predators",
      "gp": 82,
      "w": 41,
      "l": 27,
      "otl": 14,
      "pts": 96,
      "ptsPct": 0.585,
      "gf": 228,
      "ga": 215,
      "gd": 13,
      "ppPct": 0,
      "pkPct": 0,
      "conf": "West",
      "div": "Central",
      "homeW": 23,
      "homeL": 11,
      "homeOTL": 7,
      "roadW": 18,
      "roadL": 16,
      "roadOTL": 7,
      "cfPct": 52.47,
      "hdcfPct": 54.77,
      "scfPct": 53.94,
      "pdo": 0.995,
      "shPct": 7.31,
      "svPct": 92.16,
      "cf": 3670,
      "ca": 3324,
      "hdcf": 608,
      "hdca": 502,
      "hasAdvanced": true,
      "wonCup": false,
      "cupFinalist": false
    },
    "PHI": {
      "team": "PHI",
      "name": "Philadelphia Flyers",
      "gp": 81,
      "w": 40,
      "l": 27,
      "otl": 14,
      "pts": 94,
      "ptsPct": 0.58,
      "gf": 209,
      "ga": 216,
      "gd": -7,
      "ppPct": 0,
      "pkPct": 0,
      "conf": "East",
      "div": "Metropolitan",
      "homeW": 23,
      "homeL": 10,
      "homeOTL": 8,
      "roadW": 17,
      "roadL": 17,
      "roadOTL": 6,
      "cfPct": 50.59,
      "hdcfPct": 49.76,
      "scfPct": 48.71,
      "pdo": 1.004,
      "shPct": 7.07,
      "svPct": 93.36,
      "cf": 3699,
      "ca": 3612,
      "hdcf": 621,
      "hdca": 627,
      "hasAdvanced": true,
      "wonCup": false,
      "cupFinalist": false
    },
    "DET": {
      "team": "DET",
      "name": "Detroit Red Wings",
      "gp": 82,
      "w": 41,
      "l": 30,
      "otl": 11,
      "pts": 93,
      "ptsPct": 0.567,
      "gf": 211,
      "ga": 224,
      "gd": -13,
      "ppPct": 0,
      "pkPct": 0,
      "conf": "East",
      "div": "Atlantic",
      "homeW": 22,
      "homeL": 13,
      "homeOTL": 6,
      "roadW": 19,
      "roadL": 17,
      "roadOTL": 5,
      "cfPct": 51.73,
      "hdcfPct": 48.83,
      "scfPct": 51.19,
      "pdo": 0.996,
      "shPct": 7.01,
      "svPct": 92.63,
      "cf": 3403,
      "ca": 3176,
      "hdcf": 625,
      "hdca": 655,
      "hasAdvanced": true,
      "wonCup": false,
      "cupFinalist": false
    },
    "BOS": {
      "team": "BOS",
      "name": "Boston Bruins",
      "gp": 82,
      "w": 42,
      "l": 31,
      "otl": 9,
      "pts": 93,
      "ptsPct": 0.567,
      "gf": 240,
      "ga": 230,
      "gd": 10,
      "ppPct": 0,
      "pkPct": 0,
      "conf": "East",
      "div": "Atlantic",
      "homeW": 17,
      "homeL": 18,
      "homeOTL": 6,
      "roadW": 25,
      "roadL": 13,
      "roadOTL": 3,
      "cfPct": 49.55,
      "hdcfPct": 48.66,
      "scfPct": 48.96,
      "pdo": 1.0,
      "shPct": 7.73,
      "svPct": 92.32,
      "cf": 3607,
      "ca": 3673,
      "hdcf": 583,
      "hdca": 615,
      "hasAdvanced": true,
      "wonCup": false,
      "cupFinalist": false
    },
    "MIN": {
      "team": "MIN",
      "name": "Minnesota Wild",
      "gp": 82,
      "w": 38,
      "l": 33,
      "otl": 11,
      "pts": 87,
      "ptsPct": 0.53,
      "gf": 216,
      "ga": 206,
      "gd": 10,
      "ppPct": 0,
      "pkPct": 0,
      "conf": "West",
      "div": "Central",
      "homeW": 21,
      "homeL": 16,
      "homeOTL": 4,
      "roadW": 17,
      "roadL": 17,
      "roadOTL": 7,
      "cfPct": 47.86,
      "hdcfPct": 49.27,
      "scfPct": 48.49,
      "pdo": 1.007,
      "shPct": 7.65,
      "svPct": 93.05,
      "cf": 3354,
      "ca": 3654,
      "hdcf": 604,
      "hdca": 622,
      "hasAdvanced": true,
      "wonCup": false,
      "cupFinalist": false
    },
    "CAR": {
      "team": "CAR",
      "name": "Carolina Hurricanes",
      "gp": 82,
      "w": 35,
      "l": 31,
      "otl": 16,
      "pts": 86,
      "ptsPct": 0.524,
      "gf": 198,
      "ga": 226,
      "gd": -28,
      "ppPct": 0,
      "pkPct": 0,
      "conf": "East",
      "div": "Metropolitan",
      "homeW": 19,
      "homeL": 15,
      "homeOTL": 7,
      "roadW": 16,
      "roadL": 16,
      "roadOTL": 9,
      "cfPct": 51.45,
      "hdcfPct": 48.92,
      "scfPct": 49.48,
      "pdo": 0.983,
      "shPct": 6.89,
      "svPct": 91.45,
      "cf": 3682,
      "ca": 3474,
      "hdcf": 702,
      "hdca": 733,
      "hasAdvanced": true,
      "wonCup": false,
      "cupFinalist": false
    },
    "OTT": {
      "team": "OTT",
      "name": "Ottawa Senators",
      "gp": 82,
      "w": 38,
      "l": 35,
      "otl": 9,
      "pts": 85,
      "ptsPct": 0.518,
      "gf": 236,
      "ga": 247,
      "gd": -11,
      "ppPct": 0,
      "pkPct": 0,
      "conf": "East",
      "div": "Atlantic",
      "homeW": 21,
      "homeL": 14,
      "homeOTL": 6,
      "roadW": 17,
      "roadL": 21,
      "roadOTL": 3,
      "cfPct": 47.45,
      "hdcfPct": 48.0,
      "scfPct": 46.27,
      "pdo": 1.012,
      "shPct": 8.25,
      "svPct": 92.95,
      "cf": 3466,
      "ca": 3838,
      "hdcf": 636,
      "hdca": 689,
      "hasAdvanced": true,
      "wonCup": false,
      "cupFinalist": false
    },
    "NJ": {
      "team": "NJ",
      "name": "New Jersey Devils",
      "gp": 82,
      "w": 38,
      "l": 36,
      "otl": 8,
      "pts": 84,
      "ptsPct": 0.512,
      "gf": 184,
      "ga": 208,
      "gd": -24,
      "ppPct": 0,
      "pkPct": 0,
      "conf": "East",
      "div": "Metropolitan",
      "homeW": 19,
      "homeL": 17,
      "homeOTL": 5,
      "roadW": 19,
      "roadL": 19,
      "roadOTL": 3,
      "cfPct": 46.17,
      "hdcfPct": 48.33,
      "scfPct": 47.73,
      "pdo": 0.997,
      "shPct": 7.23,
      "svPct": 92.43,
      "cf": 2725,
      "ca": 3177,
      "hdcf": 521,
      "hdca": 557,
      "hasAdvanced": true,
      "wonCup": false,
      "cupFinalist": false
    },
    "COL": {
      "team": "COL",
      "name": "Colorado Avalanche",
      "gp": 82,
      "w": 39,
      "l": 39,
      "otl": 4,
      "pts": 82,
      "ptsPct": 0.5,
      "gf": 216,
      "ga": 240,
      "gd": -24,
      "ppPct": 0,
      "pkPct": 0,
      "conf": "West",
      "div": "Central",
      "homeW": 17,
      "homeL": 20,
      "homeOTL": 4,
      "roadW": 22,
      "roadL": 19,
      "roadOTL": 0,
      "cfPct": 44.2,
      "hdcfPct": 42.78,
      "scfPct": 42.82,
      "pdo": 1.005,
      "shPct": 7.79,
      "svPct": 92.72,
      "cf": 3197,
      "ca": 4036,
      "hdcf": 548,
      "hdca": 733,
      "hasAdvanced": true,
      "wonCup": false,
      "cupFinalist": false
    },
    "MTL": {
      "team": "MTL",
      "name": "Montr\u00e9al Canadiens",
      "gp": 82,
      "w": 38,
      "l": 38,
      "otl": 6,
      "pts": 82,
      "ptsPct": 0.5,
      "gf": 221,
      "ga": 236,
      "gd": -15,
      "ppPct": 0,
      "pkPct": 0,
      "conf": "East",
      "div": "Atlantic",
      "homeW": 22,
      "homeL": 16,
      "homeOTL": 3,
      "roadW": 16,
      "roadL": 22,
      "roadOTL": 3,
      "cfPct": 51.53,
      "hdcfPct": 51.42,
      "scfPct": 49.72,
      "pdo": 0.993,
      "shPct": 7.38,
      "svPct": 91.89,
      "cf": 3696,
      "ca": 3477,
      "hdcf": 689,
      "hdca": 651,
      "hasAdvanced": true,
      "wonCup": false,
      "cupFinalist": false
    },
    "BUF": {
      "team": "BUF",
      "name": "Buffalo Sabres",
      "gp": 82,
      "w": 35,
      "l": 36,
      "otl": 11,
      "pts": 81,
      "ptsPct": 0.494,
      "gf": 201,
      "ga": 222,
      "gd": -21,
      "ppPct": 0,
      "pkPct": 0,
      "conf": "East",
      "div": "Atlantic",
      "homeW": 16,
      "homeL": 19,
      "homeOTL": 6,
      "roadW": 19,
      "roadL": 17,
      "roadOTL": 5,
      "cfPct": 47.5,
      "hdcfPct": 48.74,
      "scfPct": 48.55,
      "pdo": 0.991,
      "shPct": 6.57,
      "svPct": 92.51,
      "cf": 3325,
      "ca": 3675,
      "hdcf": 598,
      "hdca": 629,
      "hasAdvanced": true,
      "wonCup": false,
      "cupFinalist": false
    },
    "ARI": {
      "team": "ARI",
      "name": "Arizona Coyotes",
      "gp": 82,
      "w": 35,
      "l": 39,
      "otl": 8,
      "pts": 78,
      "ptsPct": 0.476,
      "gf": 209,
      "ga": 245,
      "gd": -36,
      "ppPct": 0,
      "pkPct": 0,
      "conf": "West",
      "div": "Pacific",
      "homeW": 22,
      "homeL": 15,
      "homeOTL": 4,
      "roadW": 13,
      "roadL": 24,
      "roadOTL": 4,
      "cfPct": 46.8,
      "hdcfPct": 48.37,
      "scfPct": 45.91,
      "pdo": 1.007,
      "shPct": 7.79,
      "svPct": 92.96,
      "cf": 3231,
      "ca": 3673,
      "hdcf": 594,
      "hdca": 634,
      "hasAdvanced": true,
      "wonCup": false,
      "cupFinalist": false
    },
    "WPG": {
      "team": "WPG",
      "name": "Winnipeg Jets",
      "gp": 82,
      "w": 35,
      "l": 39,
      "otl": 8,
      "pts": 78,
      "ptsPct": 0.476,
      "gf": 215,
      "ga": 239,
      "gd": -24,
      "ppPct": 0,
      "pkPct": 0,
      "conf": "West",
      "div": "Central",
      "homeW": 18,
      "homeL": 19,
      "homeOTL": 4,
      "roadW": 17,
      "roadL": 20,
      "roadOTL": 4,
      "cfPct": 51.38,
      "hdcfPct": 49.77,
      "scfPct": 51.37,
      "pdo": 0.996,
      "shPct": 7.61,
      "svPct": 92.04,
      "cf": 3547,
      "ca": 3356,
      "hdcf": 660,
      "hdca": 666,
      "hasAdvanced": true,
      "wonCup": false,
      "cupFinalist": false
    },
    "CGY": {
      "team": "CGY",
      "name": "Calgary Flames",
      "gp": 82,
      "w": 35,
      "l": 40,
      "otl": 7,
      "pts": 77,
      "ptsPct": 0.47,
      "gf": 231,
      "ga": 260,
      "gd": -29,
      "ppPct": 0,
      "pkPct": 0,
      "conf": "West",
      "div": "Pacific",
      "homeW": 21,
      "homeL": 16,
      "homeOTL": 4,
      "roadW": 14,
      "roadL": 24,
      "roadOTL": 3,
      "cfPct": 47.99,
      "hdcfPct": 47.71,
      "scfPct": 49.45,
      "pdo": 0.993,
      "shPct": 8.19,
      "svPct": 91.15,
      "cf": 3505,
      "ca": 3798,
      "hdcf": 634,
      "hdca": 695,
      "hasAdvanced": true,
      "wonCup": false,
      "cupFinalist": false
    },
    "CBJ": {
      "team": "CBJ",
      "name": "Columbus Blue Jackets",
      "gp": 82,
      "w": 34,
      "l": 40,
      "otl": 8,
      "pts": 76,
      "ptsPct": 0.463,
      "gf": 219,
      "ga": 252,
      "gd": -33,
      "ppPct": 0,
      "pkPct": 0,
      "conf": "East",
      "div": "Metropolitan",
      "homeW": 18,
      "homeL": 17,
      "homeOTL": 6,
      "roadW": 16,
      "roadL": 23,
      "roadOTL": 2,
      "cfPct": 48.01,
      "hdcfPct": 53.77,
      "scfPct": 50.24,
      "pdo": 0.998,
      "shPct": 7.9,
      "svPct": 91.89,
      "cf": 3429,
      "ca": 3714,
      "hdcf": 791,
      "hdca": 680,
      "hasAdvanced": true,
      "wonCup": false,
      "cupFinalist": false
    },
    "VAN": {
      "team": "VAN",
      "name": "Vancouver Canucks",
      "gp": 82,
      "w": 31,
      "l": 38,
      "otl": 13,
      "pts": 75,
      "ptsPct": 0.457,
      "gf": 191,
      "ga": 243,
      "gd": -52,
      "ppPct": 0,
      "pkPct": 0,
      "conf": "West",
      "div": "Pacific",
      "homeW": 15,
      "homeL": 21,
      "homeOTL": 5,
      "roadW": 16,
      "roadL": 17,
      "roadOTL": 8,
      "cfPct": 47.21,
      "hdcfPct": 44.19,
      "scfPct": 44.66,
      "pdo": 0.994,
      "shPct": 6.83,
      "svPct": 92.53,
      "cf": 3271,
      "ca": 3658,
      "hdcf": 612,
      "hdca": 773,
      "hasAdvanced": true,
      "wonCup": false,
      "cupFinalist": false
    },
    "EDM": {
      "team": "EDM",
      "name": "Edmonton Oilers",
      "gp": 82,
      "w": 31,
      "l": 43,
      "otl": 8,
      "pts": 70,
      "ptsPct": 0.427,
      "gf": 203,
      "ga": 245,
      "gd": -42,
      "ppPct": 0,
      "pkPct": 0,
      "conf": "West",
      "div": "Pacific",
      "homeW": 19,
      "homeL": 20,
      "homeOTL": 2,
      "roadW": 12,
      "roadL": 23,
      "roadOTL": 6,
      "cfPct": 48.9,
      "hdcfPct": 47.57,
      "scfPct": 48.33,
      "pdo": 0.986,
      "shPct": 7.15,
      "svPct": 91.43,
      "cf": 3577,
      "ca": 3738,
      "hdcf": 636,
      "hdca": 701,
      "hasAdvanced": true,
      "wonCup": false,
      "cupFinalist": false
    },
    "TOR": {
      "team": "TOR",
      "name": "Toronto Maple Leafs",
      "gp": 82,
      "w": 29,
      "l": 42,
      "otl": 11,
      "pts": 69,
      "ptsPct": 0.421,
      "gf": 198,
      "ga": 246,
      "gd": -48,
      "ppPct": 0,
      "pkPct": 0,
      "conf": "East",
      "div": "Atlantic",
      "homeW": 14,
      "homeL": 18,
      "homeOTL": 9,
      "roadW": 15,
      "roadL": 24,
      "roadOTL": 2,
      "cfPct": 51.35,
      "hdcfPct": 50.66,
      "scfPct": 51.66,
      "pdo": 0.983,
      "shPct": 6.36,
      "svPct": 91.92,
      "cf": 3771,
      "ca": 3573,
      "hdcf": 610,
      "hdca": 594,
      "hasAdvanced": true,
      "wonCup": false,
      "cupFinalist": false
    }
  }
}